Scrytch/__init__.py
Scrytch/events.py
Scrytch/keys.py
Scrytch/looks.py
Scrytch/motion.py
Scrytch/scrytch.py
Scrytch/sound.py
Scrytch/sprite.py
scrytch-1.0.3.dist-info/licenses/LICENSE
scrytch-1.0.3.dist-info/METADATA
scrytch-1.0.3.dist-info/WHEEL
scrytch-1.0.3.dist-info/top_level.txt
scrytch-1.0.3.dist-info/RECORD
