Metadata-Version: 2.4
Name: Scrytch
Version: 1.0.3
Summary: A Python project which imitates Scratch game logic
Author-email: Kian Metzsch <contact@ckm-tech.dev>
License-Expression: MIT
Project-URL: Homepage, https://github.com/k-metzsch/scrytch
Project-URL: Issues, https://github.com/k-metzsch/scrytch/issues
Classifier: Programming Language :: Python :: 3
Classifier: Operating System :: OS Independent
Requires-Python: >=3.12
License-File: LICENSE
Requires-Dist: pygame>=2.6.0
Dynamic: license-file
